xxl/__init__.py
xxl/xxl_py.py
xxl-0.0.1.dist-info/METADATA
xxl-0.0.1.dist-info/WHEEL
xxl-0.0.1.dist-info/top_level.txt
xxl-0.0.1.dist-info/zip-safe
xxl-0.0.1.dist-info/RECORD
