Metadata-Version: 2.1
Name: xxl
Version: 0.0.1
Summary: this is a only test file
Home-page: https://pypi.org/manage/project/xxl/
Author: hanfei321
Author-email: 1154104163@qq.com
License: UNKNOWN
Keywords: test python
Platform: UNKNOWN
